mcp_client_cli/__init__.py
mcp_client_cli/cli.py
mcp_client_cli/config.py
mcp_client_cli/const.py
mcp_client_cli/input.py
mcp_client_cli/memory.py
mcp_client_cli/output.py
mcp_client_cli/prompt.py
mcp_client_cli/storage.py
mcp_client_cli/tool.py
mcp_client_cli_gigachat-1.0.2.dist-info/METADATA
mcp_client_cli_gigachat-1.0.2.dist-info/WHEEL
mcp_client_cli_gigachat-1.0.2.dist-info/entry_points.txt
mcp_client_cli_gigachat-1.0.2.dist-info/licenses/LICENSE
mcp_client_cli_gigachat-1.0.2.dist-info/RECORD
